aiorcon/__init__.py
aiorcon/exceptions.py
aiorcon/messages.py
aiorcon/protocol.py
aiorcon/rcon.py
aiorcon-0.6.7.dist-info/DESCRIPTION.rst
aiorcon-0.6.7.dist-info/METADATA
aiorcon-0.6.7.dist-info/RECORD
aiorcon-0.6.7.dist-info/WHEEL
aiorcon-0.6.7.dist-info/metadata.json
aiorcon-0.6.7.dist-info/top_level.txt
